{
  "system_id": 2,
  "model_info": {
    "model_name": "efficiency_focused_rank_1",
    "model_path": "./results/scatter_search/trained_models/efficiency_focused_rank_1.pt",
    "filename": "efficiency_focused_rank_1.pt"
  },
  "system_metrics": {
    "num_vehicles": 49,
    "num_slots": 30,
    "num_chargers": 12,
    "system_context": {
      "total_spots": 30,
      "total_chargers": 12,
      "total_timesteps": 56,
      "transformer_limit": 100,
      "simulation_duration_hours": 13.75,
      "dt_hours": 0.25,
      "max_charger_power_total": 114,
      "theoretical_max_energy": 1596.0,
      "has_priority_system": false,
      "has_willingness_to_pay": false,
      "has_brand_compatibility": false
    }
  },
  "execution_performance": {
    "execution_time_seconds": 0.205,
    "schedule_entries": 49,
    "timesteps_used": 35,
    "time_coverage_pct": 62.5
  },
  "vehicle_performance": {
    "vehicles_assigned": 49,
    "vehicles_total": 49,
    "assignment_ratio_pct": 100.0,
    "vehicles_fully_satisfied": 0,
    "vehicles_partially_satisfied": 49,
    "vehicles_not_satisfied": 0,
    "charging_assignments": 49,
    "parking_assignments": 0
  },
  "energy_performance": {
    "total_energy_required_kwh": 1148.11,
    "total_energy_delivered_kwh": 85.75,
    "overall_satisfaction_pct": 7.5,
    "energy_deficit_kwh": 1062.36,
    "satisfaction_distribution": {
      "min_satisfaction": 0.04425903312793918,
      "max_satisfaction": 0.3361565797492185,
      "avg_satisfaction": 0.09672490767517986,
      "std_satisfaction": 0.06128751144394485
    }
  },
  "economic_performance": {
    "total_energy_cost": 3117.23,
    "avg_energy_price_per_kwh": 36.353,
    "cost_efficiency": 36.353
  },
  "resource_utilization": {
    "capacity_utilization_pct": 5.4,
    "spots_utilization_pct": 2.9,
    "chargers_utilization_pct": 7.3
  },
  "detailed_ev_metrics": {
    "0": {
      "required_energy": 17.575879323282518,
      "delivered_energy": 1.75,
      "satisfaction": 0.09956827580636606,
      "priority": 1,
      "willingness": 1.0
    },
    "1": {
      "required_energy": 29.85517976644757,
      "delivered_energy": 1.75,
      "satisfaction": 0.05861629418043964,
      "priority": 1,
      "willingness": 1.0
    },
    "2": {
      "required_energy": 38.51152241737711,
      "delivered_energy": 1.75,
      "satisfaction": 0.045440945726164486,
      "priority": 1,
      "willingness": 1.0
    },
    "3": {
      "required_energy": 27.624369684118772,
      "delivered_energy": 1.75,
      "satisfaction": 0.06334986173480271,
      "priority": 1,
      "willingness": 1.0
    },
    "4": {
      "required_energy": 14.045760705347577,
      "delivered_energy": 1.75,
      "satisfaction": 0.1245927534087727,
      "priority": 1,
      "willingness": 1.0
    },
    "5": {
      "required_energy": 11.05132243038047,
      "delivered_energy": 1.75,
      "satisfaction": 0.15835208962768013,
      "priority": 1,
      "willingness": 1.0
    },
    "6": {
      "required_energy": 20.931625385301075,
      "delivered_energy": 1.75,
      "satisfaction": 0.08360554748074708,
      "priority": 1,
      "willingness": 1.0
    },
    "7": {
      "required_energy": 7.537773468917264,
      "delivered_energy": 1.75,
      "satisfaction": 0.23216404780752484,
      "priority": 1,
      "willingness": 1.0
    },
    "8": {
      "required_energy": 34.16781743546146,
      "delivered_energy": 1.75,
      "satisfaction": 0.05121778712689276,
      "priority": 1,
      "willingness": 1.0
    },
    "9": {
      "required_energy": 37.553598119286036,
      "delivered_energy": 1.75,
      "satisfaction": 0.04660006198184428,
      "priority": 1,
      "willingness": 1.0
    },
    "10": {
      "required_energy": 20.977374603309084,
      "delivered_energy": 1.75,
      "satisfaction": 0.08342321349040245,
      "priority": 1,
      "willingness": 1.0
    },
    "11": {
      "required_energy": 14.504605379918202,
      "delivered_energy": 1.75,
      "satisfaction": 0.12065133481141761,
      "priority": 1,
      "willingness": 1.0
    },
    "12": {
      "required_energy": 15.759789558896784,
      "delivered_energy": 1.75,
      "satisfaction": 0.1110420918667713,
      "priority": 1,
      "willingness": 1.0
    },
    "13": {
      "required_energy": 32.929211969791595,
      "delivered_energy": 1.75,
      "satisfaction": 0.05314430243898349,
      "priority": 1,
      "willingness": 1.0
    },
    "14": {
      "required_energy": 34.878878609379086,
      "delivered_energy": 1.75,
      "satisfaction": 0.050173631428890524,
      "priority": 1,
      "willingness": 1.0
    },
    "15": {
      "required_energy": 25.792717030847733,
      "delivered_energy": 1.75,
      "satisfaction": 0.06784861005170661,
      "priority": 1,
      "willingness": 1.0
    },
    "16": {
      "required_energy": 22.27723454099018,
      "delivered_energy": 1.75,
      "satisfaction": 0.07855553151267473,
      "priority": 1,
      "willingness": 1.0
    },
    "17": {
      "required_energy": 11.401630225919815,
      "delivered_energy": 1.75,
      "satisfaction": 0.15348682296516247,
      "priority": 1,
      "willingness": 1.0
    },
    "18": {
      "required_energy": 6.695895208077879,
      "delivered_energy": 1.75,
      "satisfaction": 0.26135414991095035,
      "priority": 1,
      "willingness": 1.0
    },
    "19": {
      "required_energy": 37.599662616724345,
      "delivered_energy": 1.75,
      "satisfaction": 0.046542970819679626,
      "priority": 1,
      "willingness": 1.0
    },
    "20": {
      "required_energy": 30.94179114039053,
      "delivered_energy": 1.75,
      "satisfaction": 0.05655781179763701,
      "priority": 1,
      "willingness": 1.0
    },
    "21": {
      "required_energy": 29.469467563246035,
      "delivered_energy": 1.75,
      "satisfaction": 0.059383495689028974,
      "priority": 1,
      "willingness": 1.0
    },
    "22": {
      "required_energy": 32.2700749597312,
      "delivered_energy": 1.75,
      "satisfaction": 0.05422980895407803,
      "priority": 1,
      "willingness": 1.0
    },
    "23": {
      "required_energy": 34.45863348282421,
      "delivered_energy": 1.75,
      "satisfaction": 0.050785531030192524,
      "priority": 1,
      "willingness": 1.0
    },
    "24": {
      "required_energy": 17.310548803883275,
      "delivered_energy": 1.75,
      "satisfaction": 0.10109442628459142,
      "priority": 1,
      "willingness": 1.0
    },
    "25": {
      "required_energy": 33.11878888996866,
      "delivered_energy": 1.75,
      "satisfaction": 0.05284009647255117,
      "priority": 1,
      "willingness": 1.0
    },
    "26": {
      "required_energy": 30.488738007526937,
      "delivered_energy": 1.75,
      "satisfaction": 0.057398243232237654,
      "priority": 1,
      "willingness": 1.0
    },
    "27": {
      "required_energy": 16.022919425228284,
      "delivered_energy": 1.75,
      "satisfaction": 0.10921854835296765,
      "priority": 1,
      "willingness": 1.0
    },
    "28": {
      "required_energy": 39.528268190654515,
      "delivered_energy": 1.75,
      "satisfaction": 0.04427211411234415,
      "priority": 1,
      "willingness": 1.0
    },
    "29": {
      "required_energy": 25.058234265858307,
      "delivered_energy": 1.75,
      "satisfaction": 0.06983732299064521,
      "priority": 1,
      "willingness": 1.0
    },
    "30": {
      "required_energy": 25.284442414199436,
      "delivered_energy": 1.75,
      "satisfaction": 0.06921252093806195,
      "priority": 1,
      "willingness": 1.0
    },
    "31": {
      "required_energy": 26.53849897389134,
      "delivered_energy": 1.75,
      "satisfaction": 0.06594193596712669,
      "priority": 1,
      "willingness": 1.0
    },
    "32": {
      "required_energy": 24.322137345990498,
      "delivered_energy": 1.75,
      "satisfaction": 0.07195091348698791,
      "priority": 1,
      "willingness": 1.0
    },
    "33": {
      "required_energy": 23.463436046211132,
      "delivered_energy": 1.75,
      "satisfaction": 0.07458413152077908,
      "priority": 1,
      "willingness": 1.0
    },
    "34": {
      "required_energy": 12.094245747831636,
      "delivered_energy": 1.75,
      "satisfaction": 0.14469691095153706,
      "priority": 1,
      "willingness": 1.0
    },
    "35": {
      "required_energy": 5.205907322431544,
      "delivered_energy": 1.75,
      "satisfaction": 0.3361565797492185,
      "priority": 1,
      "willingness": 1.0
    },
    "36": {
      "required_energy": 7.76419151398189,
      "delivered_energy": 1.75,
      "satisfaction": 0.22539371895303842,
      "priority": 1,
      "willingness": 1.0
    },
    "37": {
      "required_energy": 22.82811143114173,
      "delivered_energy": 1.75,
      "satisfaction": 0.07665986760572227,
      "priority": 1,
      "willingness": 1.0
    },
    "38": {
      "required_energy": 25.112187895490358,
      "delivered_energy": 1.75,
      "satisfaction": 0.06968727724095536,
      "priority": 1,
      "willingness": 1.0
    },
    "39": {
      "required_energy": 14.852830506030658,
      "delivered_energy": 1.75,
      "satisfaction": 0.11782266008418071,
      "priority": 1,
      "willingness": 1.0
    },
    "40": {
      "required_energy": 19.084477464346946,
      "delivered_energy": 1.75,
      "satisfaction": 0.09169755909059066,
      "priority": 1,
      "willingness": 1.0
    },
    "41": {
      "required_energy": 14.127511324419599,
      "delivered_energy": 1.75,
      "satisfaction": 0.12387178178899073,
      "priority": 1,
      "willingness": 1.0
    },
    "42": {
      "required_energy": 37.110739865141944,
      "delivered_energy": 1.75,
      "satisfaction": 0.047156160355718804,
      "priority": 1,
      "willingness": 1.0
    },
    "43": {
      "required_energy": 10.79823453002439,
      "delivered_energy": 1.75,
      "satisfaction": 0.1620635294717985,
      "priority": 1,
      "willingness": 1.0
    },
    "44": {
      "required_energy": 19.301281334301322,
      "delivered_energy": 1.75,
      "satisfaction": 0.09066755567621218,
      "priority": 1,
      "willingness": 1.0
    },
    "45": {
      "required_energy": 39.53995097320113,
      "delivered_energy": 1.75,
      "satisfaction": 0.04425903312793918,
      "priority": 1,
      "willingness": 1.0
    },
    "46": {
      "required_energy": 33.572910603695426,
      "delivered_energy": 1.75,
      "satisfaction": 0.052125358467054524,
      "priority": 1,
      "willingness": 1.0
    },
    "47": {
      "required_energy": 10.736560919821326,
      "delivered_energy": 1.75,
      "satisfaction": 0.16299446471441648,
      "priority": 1,
      "willingness": 1.0
    },
    "48": {
      "required_energy": 26.0297387715397,
      "delivered_energy": 1.75,
      "satisfaction": 0.06723079379933726,
      "priority": 1,
      "willingness": 1.0
    }
  },
  "schedule_detail": [
    [
      0,
      1,
      0,
      0,
      7
    ],
    [
      1,
      2,
      0,
      0,
      7
    ],
    [
      2,
      3,
      0,
      0,
      7
    ],
    [
      3,
      3,
      1,
      1,
      7
    ],
    [
      4,
      5,
      0,
      0,
      7
    ],
    [
      5,
      6,
      0,
      0,
      7
    ],
    [
      6,
      6,
      1,
      1,
      7
    ],
    [
      7,
      7,
      0,
      0,
      7
    ],
    [
      8,
      7,
      1,
      1,
      7
    ],
    [
      9,
      7,
      2,
      2,
      7
    ],
    [
      10,
      7,
      3,
      3,
      7
    ],
    [
      11,
      8,
      0,
      0,
      7
    ],
    [
      12,
      9,
      0,
      0,
      7
    ],
    [
      13,
      10,
      0,
      0,
      7
    ],
    [
      14,
      11,
      0,
      0,
      7
    ],
    [
      15,
      12,
      0,
      0,
      7
    ],
    [
      16,
      13,
      0,
      0,
      7
    ],
    [
      17,
      13,
      1,
      1,
      7
    ],
    [
      18,
      13,
      2,
      2,
      7
    ],
    [
      19,
      14,
      0,
      0,
      7
    ],
    [
      20,
      16,
      0,
      0,
      7
    ],
    [
      21,
      19,
      0,
      0,
      7
    ],
    [
      22,
      26,
      0,
      0,
      7
    ],
    [
      23,
      27,
      0,
      0,
      7
    ],
    [
      24,
      28,
      0,
      0,
      7
    ],
    [
      25,
      29,
      0,
      0,
      7
    ],
    [
      26,
      30,
      0,
      0,
      7
    ],
    [
      27,
      31,
      0,
      0,
      7
    ],
    [
      28,
      31,
      1,
      1,
      7
    ],
    [
      29,
      32,
      0,
      0,
      7
    ],
    [
      30,
      33,
      0,
      0,
      7
    ],
    [
      31,
      33,
      1,
      1,
      7
    ],
    [
      32,
      33,
      2,
      2,
      7
    ],
    [
      33,
      34,
      0,
      0,
      7
    ],
    [
      34,
      35,
      0,
      0,
      7
    ],
    [
      35,
      35,
      1,
      1,
      7
    ],
    [
      36,
      36,
      0,
      0,
      7
    ],
    [
      37,
      36,
      1,
      1,
      7
    ],
    [
      38,
      41,
      0,
      0,
      7
    ],
    [
      39,
      42,
      0,
      0,
      7
    ],
    [
      40,
      44,
      0,
      0,
      7
    ],
    [
      41,
      45,
      0,
      0,
      7
    ],
    [
      42,
      47,
      0,
      0,
      7
    ],
    [
      43,
      47,
      1,
      1,
      7
    ],
    [
      44,
      47,
      2,
      2,
      7
    ],
    [
      45,
      48,
      0,
      0,
      7
    ],
    [
      46,
      50,
      0,
      0,
      7
    ],
    [
      47,
      54,
      0,
      0,
      7
    ],
    [
      48,
      55,
      0,
      0,
      7
    ]
  ],
  "timestamp": "2025-06-01 19:11:21"
}